cloudcoil/models/kpack/__init__.py
cloudcoil/models/kpack/core.py
cloudcoil/models/kpack/py.typed
cloudcoil/models/kpack/v1alpha1.py
cloudcoil/models/kpack/v1alpha2.py
cloudcoil_models_kpack-0.16.1.0.dist-info/METADATA
cloudcoil_models_kpack-0.16.1.0.dist-info/WHEEL
cloudcoil_models_kpack-0.16.1.0.dist-info/licenses/LICENSE
cloudcoil_models_kpack-0.16.1.0.dist-info/RECORD
